{
 "actions": [],
 "allow_rename": 1,
 "creation": "2022-03-22 15:52:16.909909",
 "doctype": "DocType",
 "editable_grid": 1,
 "engine": "InnoDB",
 "field_order": [
  "section",
  "day_time",
  "room"
 ],
 "fields": [
  {
   "fieldname": "section",
   "fieldtype": "Data",
   "in_list_view": 1,
   "label": "Section",
   "reqd": 1
  },
  {
   "fieldname": "day_time",
   "fieldtype": "Data",
   "in_list_view": 1,
   "label": "Day/Time",
   "reqd": 1
  },
  {
   "fieldname": "room",
   "fieldtype": "Data",
   "in_list_view": 1,
   "label": "Room",
   "reqd": 1
  }
 ],
 "index_web_pages_for_search": 1,
 "istable": 1,
 "links": [],
 "modified": "2022-03-22 15:58:56.995032",
 "modified_by": "Administrator",
 "module": "Course Syllabus Builder",
 "name": "Course Schedule",
 "owner": "Administrator",
 "permissions": [],
 "sort_field": "modified",
 "sort_order": "DESC"
}